Image_Processing/__init__.py
Image_Processing/Processing/Transformation.py
Image_Processing/Processing/__init__.py
Image_Processing/Processing/combination.py
Image_Processing/Utils/__init__.py
Image_Processing/Utils/io.py
Image_Processing/Utils/plot.py
Processamento_de_imagem_Desafio_DIO-0.0.1.dist-info/METADATA
Processamento_de_imagem_Desafio_DIO-0.0.1.dist-info/WHEEL
Processamento_de_imagem_Desafio_DIO-0.0.1.dist-info/top_level.txt
Processamento_de_imagem_Desafio_DIO-0.0.1.dist-info/RECORD
