Metadata-Version: 2.1
Name: Processamento-de-imagem-Desafio-DIO
Version: 0.0.1
Summary: Image Processing Package using Skimage
Home-page: https://github.com/gabriellivieira/Bootcamp_data_science/tree/main/desafios/Pacotes_Processamento_Imagem_Python
Author: Gabrielli
Requires-Python: >=3.8
Requires-Dist: matplotlib
Requires-Dist: numpy
Requires-Dist: scikit-image (>=0.16.1)
